convert.py
utaromkan.py
utaromkan-1.4.0.dist-info/LICENSE
utaromkan-1.4.0.dist-info/WHEEL
utaromkan-1.4.0.dist-info/METADATA
utaromkan-1.4.0.dist-info/RECORD
