Metadata-Version: 2.1
Name: utaromkan
Version: 1.4.0
Summary: kana <-> romaji conversion for utau
Home-page: http://github.com/danalog/utaromkan/
Author: Tart
Author-email: conemusicproductions@gmail.com
Classifier: Programming Language :: Python :: 2
Classifier: Programming Language :: Python :: 2.7
Classifier: Programming Language :: Python :: 3
Classifier: Programming Language :: Python :: 3.4
Classifier: Programming Language :: Python :: 3.5
Classifier: Programming Language :: Python :: 3.6
Classifier: Programming Language :: Python :: 3.7
Classifier: Programming Language :: Python :: 3.8
Project-URL: Repository, http://github.com/danalog/utaromkan/
